pinybytecnn-1.0.0.dist-info/licenses/LICENSE
tinybytecnn/__init__.py
tinybytecnn/accuracy_validation.py
tinybytecnn/layers.py
tinybytecnn/model.py
tinybytecnn/multi_layer_optimized.py
tinybytecnn/utils.py
pinybytecnn-1.0.0.dist-info/METADATA
pinybytecnn-1.0.0.dist-info/WHEEL
pinybytecnn-1.0.0.dist-info/top_level.txt
pinybytecnn-1.0.0.dist-info/RECORD
