Metadata-Version: 2.4
Name: pinybytecnn
Version: 1.0.0
Summary: Pure Python ByteCNN for edge deployment
Author: PinyByteCNN Contributors
License: MIT
Project-URL: Homepage, https://github.com/mitchins/pinybytecnn
Project-URL: Repository, https://github.com/mitchins/pinybytecnn
Project-URL: Issues, https://github.com/mitchins/pinybytecnn/issues
Keywords: neural-network,cnn,text-classification,edge-computing,pure-python
Classifier: Development Status :: 4 - Beta
Classifier: Intended Audience :: Developers
Classifier: License :: OSI Approved :: MIT License
Classifier: Programming Language :: Python :: 3
Classifier: Programming Language :: Python :: 3.10
Classifier: Programming Language :: Python :: 3.11
Classifier: Programming Language :: Python :: 3.12
Classifier: Topic :: Scientific/Engineering :: Artificial Intelligence
Requires-Python: >=3.10
License-File: LICENSE
Provides-Extra: dev
Requires-Dist: ruff>=0.1.0; extra == "dev"
Requires-Dist: mypy>=1.0.0; extra == "dev"
Requires-Dist: bandit>=1.7.0; extra == "dev"
Requires-Dist: safety>=2.0.0; extra == "dev"
Requires-Dist: coverage>=7.0.0; extra == "dev"
Dynamic: license-file
